eng2urdu/__init__.py
eng2urdu/convertor.py
eng2urdu-0.1.0.dist-info/METADATA
eng2urdu-0.1.0.dist-info/WHEEL
eng2urdu-0.1.0.dist-info/top_level.txt
eng2urdu-0.1.0.dist-info/RECORD
